{
  "title": "Renai Daikou Abridged",
  "description": "The Renai Daikou Abridged Series by the Second Manga Research Club based on Renai Daikou.",
  "artist": "Nobuko Taishi Seki",
  "author": "The Second Manga Research Club",
  "cover": "https://i.imgur.com/a11KGWO.png",
  "chapters": {
    "25": {
      "title": "25",
      "volume": "1",
      "last_updated": "1707538261",
      "groups": {
        "The Second Manga Research Club": [
          "https://i.imgur.com/awIwaZg.png",
          "https://i.imgur.com/o2yMmln.png"
        ]
      }
    }
  }
}